aoa/__init__.py
aoa/context/__init__.py
aoa/crypto/__init__.py
aoa/stats/__init__.py
aoa/stats/stats/__init__.py
aoa/stats/store/__init__.py
aoa/util/__init__.py
aoa/util/connections/__init__.py
teradatamodelops-7.2.3.dist-info/licenses/LICENSE-3RD-PARTY.txt
teradatamodelops-7.2.3.dist-info/licenses/LICENSE.txt
tmo/__init__.py
tmo/api_client.py
tmo/spinner.py
tmo/tmo_cli.py
tmo/api/__init__.py
tmo/api/api_iterator.py
tmo/api/base_api.py
tmo/api/dataset_api.py
tmo/api/dataset_connection_api.py
tmo/api/dataset_template_api.py
tmo/api/deployment_api.py
tmo/api/feature_engineering_api.py
tmo/api/iterator_base_api.py
tmo/api/job_api.py
tmo/api/job_event_api.py
tmo/api/message_api.py
tmo/api/model_api.py
tmo/api/project_api.py
tmo/api/trained_model_api.py
tmo/api/trained_model_artefacts_api.py
tmo/api/trained_model_event_api.py
tmo/api/user_attributes_api.py
tmo/cli/__init__.py
tmo/cli/base_model.py
tmo/cli/base_task.py
tmo/cli/evaluate_model.py
tmo/cli/model_utils.py
tmo/cli/repo_manager.py
tmo/cli/run_model.R
tmo/cli/run_task.py
tmo/cli/score_model.py
tmo/cli/train_model.py
tmo/cli/metadata_files/.gitignore
tmo/cli/metadata_files/readme.md
tmo/context/__init__.py
tmo/context/model_context.py
tmo/crypto/TJEncryptPassword.py
tmo/crypto/__init__.py
tmo/crypto/crypto.py
tmo/decorators/__init__.py
tmo/decorators/functional.py
tmo/docs/pypi.md
tmo/examples/byom_import.ipynb
tmo/examples/byom_lifecycle.ipynb
tmo/examples/developer_experience.ipynb
tmo/examples/feature_engineering.ipynb
tmo/examples/register_dataset_connection.ipynb
tmo/examples/schedule_notebook.ipynb
tmo/examples/artifacts/BYO_Notebook.ipynb
tmo/examples/artifacts/model.pmml
tmo/examples/artifacts/pima.pmml
tmo/examples/artifacts/requirements.txt
tmo/examples/artifacts/task.py
tmo/stats/__init__.py
tmo/stats/stats.py
tmo/stats/stats_util.py
tmo/stats/store.py
tmo/types/__init__.py
tmo/types/base_dataset.py
tmo/types/dataset.py
tmo/types/dataset_metadata.py
tmo/types/dataset_template.py
tmo/types/entity.py
tmo/types/exceptions.py
tmo/types/job.py
tmo/util/__init__.py
tmo/util/artifacts.py
tmo/util/byom.py
teradatamodelops-7.2.3.dist-info/METADATA
teradatamodelops-7.2.3.dist-info/WHEEL
teradatamodelops-7.2.3.dist-info/entry_points.txt
teradatamodelops-7.2.3.dist-info/top_level.txt
teradatamodelops-7.2.3.dist-info/RECORD
