Metadata-Version: 2.4
Name: teradatamodelops
Version: 7.2.3
Summary: Python client for Teradata ModelOps (TMO)
Author-email: Christian Axel Schmidt Dick <christianaxel.schmidt@teradata.com>, Anton Zadorozhniy <anton.zadorozhniy@teradata.com>, Sheheryar Ali Bhatti <sheheryar.bhatti@teradata.com>, Will Fleury <will.fleury@teradata.com>, Mengyu Mo <mengyu.mo@teradata.com>, Hiya Devli <hiya.devli@teradata.com>
Maintainer-email: Christian Axel Schmidt Dick <christianaxel.schmidt@teradata.com>, Anton Zadorozhniy <anton.zadorozhniy@teradata.com>, Mengyu Mo <mengyu.mo@teradata.com>, Hiya Devli <hiya.devli@teradata.com>
License: Copyright (c) 2024 Teradata. All rights reserved.
Project-URL: Homepage, https://pypi.org/project/teradatamodelops/
Project-URL: Documentation, https://pypi.org/project/teradatamodelops/#cli
Project-URL: Repository, https://github.com/Teradata-PE/avmo-ModelOpsPythonSDK
Project-URL: Changelog, https://github.com/Teradata-PE/avmo-ModelOpsPythonSDK/CHANGELOG.md
Keywords: teradata,vantage,data science,devops,vantagecloud
Classifier: Development Status :: 5 - Production/Stable
Classifier: Intended Audience :: Developers
Classifier: Intended Audience :: Financial and Insurance Industry
Classifier: Intended Audience :: Healthcare Industry
Classifier: Intended Audience :: Information Technology
Classifier: Intended Audience :: Manufacturing
Classifier: Intended Audience :: Other Audience
Classifier: Intended Audience :: Science/Research
Classifier: License :: Other/Proprietary License
Classifier: Programming Language :: Python :: 3.10
Classifier: Programming Language :: Python :: 3.11
Classifier: Programming Language :: Python :: 3.12
Classifier: Programming Language :: Python :: 3.13
Classifier: Programming Language :: Python :: 3.14
Classifier: Topic :: Database
Classifier: Topic :: Scientific/Engineering :: Artificial Intelligence
Classifier: Topic :: Utilities
Requires-Python: >=3.10
License-File: LICENSE-3RD-PARTY.txt
License-File: LICENSE.txt
Requires-Dist: jinja2>=3.1.6
Requires-Dist: requests>=2.32.5
Requires-Dist: requests-oauthlib>=2.0.0
Requires-Dist: oauthlib>=3.3.1
Requires-Dist: aia>=0.2.0
Requires-Dist: pyyaml>=6.0.3
Requires-Dist: gitpython>=3.1.45
Requires-Dist: cryptography>=46.0.3
Requires-Dist: teradataml>=20.0.0.8
Requires-Dist: certifi>=2025.11.12
Requires-Dist: matplotlib>=3.10.7
Requires-Dist: numpy==1.26.4
Requires-Dist: pandas>=2.3.3
Dynamic: license-file
